setup.py
gaussian_bionary_dist_prob/Binomialdistribution.py
gaussian_bionary_dist_prob/Gaussiandistribution.py
gaussian_bionary_dist_prob/Generaldistribution.py
gaussian_bionary_dist_prob/__init__.py
gaussian_bionary_dist_prob.egg-info/PKG-INFO
gaussian_bionary_dist_prob.egg-info/SOURCES.txt
gaussian_bionary_dist_prob.egg-info/dependency_links.txt
gaussian_bionary_dist_prob.egg-info/not-zip-safe
gaussian_bionary_dist_prob.egg-info/top_level.txt