Metadata-Version: 1.0
Name: gaussian-bionary-dist-prob
Version: 0.1
Summary: Gaussian and Binomial distributions
Home-page: UNKNOWN
Author: Stefanie Si
Author-email: surily823@gmail.com
License: UNKNOWN
Platform: UNKNOWN
